Workbook

Sheet Supplier_Risk_Pivot
A3: Row Labels | B3: Sum of Shortge_Value
A4: Delta | B4: 2.7174751e+08
A5: Nova | B5: 2.5339676e+08
A6: Alpha | B6: 2.4065227e+08
A7: Sigma | B7: 2.2882678e+08
A8: Beta | B8: 2.2852507e+08
A9: Grand Total | B9: 1.2231484e+09

Sheet Shortage_Value_Pivot
A3: Row Labels | B3: Sum of Shortge_Value
A4: Cooling | B4: 2.678798e+08
A5: Memory | B5: 2.6625968e+08
A6: GPU | B6: 2.4279536e+08
A7: CPU | B7: 2.2889999e+08
A8: Board | B8: 2.1731356e+08
A9: Grand Total | B9: 1.2231484e+09

Sheet Inventory_Risk_pivot
B3: Column Labels
B4: High Risk | D4: Sufficuent Stock | F4: Total Count of Product_ID | G4: Total Count of Product_ID2
A5: Row Labels | B5: Count of Product_ID | C5: Count of Product_ID2 | D5: Count of Product_ID | E5: Count of Product_ID2
A6: Cooling | B6: 353 | C6: 0.57027464 | D6: 266 | E6: 0.42972536 | F6: 619 | G6: 1
A7: Memory | B7: 322 | C7: 0.5322314 | D7: 283 | E7: 0.4677686 | F7: 605 | G7: 1
A8: GPU | B8: 321 | C8: 0.5136 | D8: 304 | E8: 0.4864 | F8: 625 | G8: 1
A9: CPU | B9: 318 | C9: 0.53716216 | D9: 274 | E9: 0.46283784 | F9: 592 | G9: 1
A10: Board | B10: 290 | C10: 0.51878354 | D10: 269 | E10: 0.48121646 | F10: 559 | G10: 1
A11: Grand Total | B11: 1604 | C11: 0.53466667 | D11: 1396 | E11: 0.46533333 | F11: 3000 | G11: 1

Sheet COGS_Category_Pivot
A3: Row Labels | B3: Budget COGS | C3: Actual COGS
A4: Board | B4: 2.8493147e+08 | C4: 2.9771257e+08
A5: Cooling | B5: 3.0408587e+08 | C5: 3.2270194e+08
A6: CPU | B6: 2.9347067e+08 | C6: 3.0895654e+08
A7: GPU | B7: 3.2743276e+08 | C7: 3.4633967e+08
A8: Memory | B8: 3.084112e+08 | C8: 3.2432941e+08
A9: Grand Total | B9: 1.518332e+09 | C9: 1.6000401e+09

Sheet Inventory
A1: Date | B1: Product_ID | C1: Category | D1: Supplier | E1: Qty_On_Hand | F1: Unit_Cost | G1: Std_Cost | H1: Actual_Cost | I1: Monthly_Demand | J1: Lead_Time_Days | K1: Demand_During_Lead_Time | L1: Stock_Risk | N1: Total High Risk Products | O1: High_risk_rate | P1: Shortage_Qty | Q1: Total Shortage | R1: Shortge_Value | S1: Total Shortage Value | T1: Budget_COGS_Calculated | U1: Actual_COGS_Calculated | V1: COGS_Variance | W1: COGS_Variance %
A2: 2025-03-11 | B2: P02724 | C2: Cooling | D2: Beta | E2: 0 | F2: 404.82 | G2: 377.31 | H2: 404.82 | I2: 3473 | J2: 65 | K2: =(I2/30)*J2 -> 7524.8333 | L2: =IF(E2<K2,"High Risk","Sufficuent Stock") -> High Risk | N2: {=SUMPRODUCT(--(E2:E3001<K2:K3001))} -> 1604 | O2: =N2/COUNTA(B2:B3001) -> 0.53466667 | P2: =ROUNDUP(MAX(0,K2-E2),0) -> 7525 | Q2: =SUM(P2:P3001) -> 4760154 | R2: =P2*H2 -> 3046270.5 | S2: =SUM(R2:R3001) -> 1.2231484e+09 | T2: =I2*G2 -> 1310397.6 | U2: =I2*H2 -> 1405939.9 | V2: =U2-T2 -> 95542.23 | W2: =IFERROR(V2/T2,0) -> 0.072910869
A3: 2025-09-10 | B3: P01446 | C3: CPU | D3: Delta | E3: 1 | F3: 312.38 | G3: 293.04 | H3: 312.38 | I3: 222 | J3: 20 | K3: =(I3/30)*J3 -> 148 | L3: =IF(E3<K3,"High Risk","Sufficuent Stock") -> High Risk | P3: =ROUNDUP(MAX(0,K3-E3),0) -> 147 | R3: =P3*H3 -> 45919.86 | T3: =I3*G3 -> 65054.88 | U3: =I3*H3 -> 69348.36 | V3: =U3-T3 -> 4293.48 | W3: =IFERROR(V3/T3,0) -> 0.065997816
A4: 2025-05-31 | B4: P02229 | C4: Cooling | D4: Nova | E4: 2 | F4: 426.73 | G4: 401.69 | H4: 426.73 | I4: 1248 | J4: 13 | K4: =(I4/30)*J4 -> 540.8 | L4: =IF(E4<K4,"High Risk","Sufficuent Stock") -> High Risk | P4: =ROUNDUP(MAX(0,K4-E4),0) -> 539 | R4: =P4*H4 -> 230007.47 | T4: =I4*G4 -> 501309.12 | U4: =I4*H4 -> 532559.04 | V4: =U4-T4 -> 31249.92 | W4: =IFERROR(V4/T4,0) -> 0.062336628
A5: 2025-09-13 | B5: P01383 | C5: Cooling | D5: Nova | E5: 2 | F5: 43.18 | G5: 41.67 | H5: 43.18 | I5: 3110 | J5: 68 | K5: =(I5/30)*J5 -> 7049.3333 | L5: =IF(E5<K5,"High Risk","Sufficuent Stock") -> High Risk | P5: =ROUNDUP(MAX(0,K5-E5),0) -> 7048 | R5: =P5*H5 -> 304332.64 | T5: =I5*G5 -> 129593.7 | U5: =I5*H5 -> 134289.8 | V5: =U5-T5 -> 4696.1 | W5: =IFERROR(V5/T5,0) -> 0.036237101
A6: 2025-07-27 | B6: P00073 | C6: CPU | D6: Delta | E6: 3 | F6: 138.87 | G6: 139.68 | H6: 138.87 | I6: 1170 | J6: 89 | K6: =(I6/30)*J6 -> 3471 | L6: =IF(E6<K6,"High Risk","Sufficuent Stock") -> High Risk | P6: =ROUNDUP(MAX(0,K6-E6),0) -> 3468 | R6: =P6*H6 -> 481601.16 | T6: =I6*G6 -> 163425.6 | U6: =I6*H6 -> 162477.9 | V6: =U6-T6 -> -947.7 | W6: =IFERROR(V6/T6,0) -> -0.0057989691
A7: 2025-09-08 | B7: P02129 | C7: GPU | D7: Beta | E7: 6 | F7: 223.54 | G7: 240.42 | H7: 223.54 | I7: 316 | J7: 71 | K7: =(I7/30)*J7 -> 747.86667 | L7: =IF(E7<K7,"High Risk","Sufficuent Stock") -> High Risk | P7: =ROUNDUP(MAX(0,K7-E7),0) -> 742 | R7: =P7*H7 -> 165866.68 | T7: =I7*G7 -> 75972.72 | U7: =I7*H7 -> 70638.64 | V7: =U7-T7 -> -5334.08 | W7: =IFERROR(V7/T7,0) -> -0.070210465
A8: 2025-10-29 | B8: P00619 | C8: Board | D8: Delta | E8: 6 | F8: 407.54 | G8: 388.55 | H8: 407.54 | I8: 1505 | J8: 12 | K8: =(I8/30)*J8 -> 602 | L8: =IF(E8<K8,"High Risk","Sufficuent Stock") -> High Risk | P8: =ROUNDUP(MAX(0,K8-E8),0) -> 596 | R8: =P8*H8 -> 242893.84 | T8: =I8*G8 -> 584767.75 | U8: =I8*H8 -> 613347.7 | V8: =U8-T8 -> 28579.95 | W8: =IFERROR(V8/T8,0) -> 0.048874019
A9: 2025-06-27 | B9: P01806 | C9: GPU | D9: Sigma | E9: 7 | F9: 443.34 | G9: 395.18 | H9: 443.34 | I9: 3164 | J9: 10 | K9: =(I9/30)*J9 -> 1054.6667 | L9: =IF(E9<K9,"High Risk","Sufficuent Stock") -> High Risk | P9: =ROUNDUP(MAX(0,K9-E9),0) -> 1048 | R9: =P9*H9 -> 464620.32 | T9: =I9*G9 -> 1250349.5 | U9: =I9*H9 -> 1402727.8 | V9: =U9-T9 -> 152378.24 | W9: =IFERROR(V9/T9,0) -> 0.12186852
A10: 2025-02-16 | B10: P00588 | C10: Board | D10: Delta | E10: 9 | F10: 468.93 | G10: 492.71 | H10: 468.93 | I10: 2885 | J10: 8 | K10: =(I10/30)*J10 -> 769.33333 | L10: =IF(E10<K10,"High Risk","Sufficuent Stock") -> High Risk | P10: =ROUNDUP(MAX(0,K10-E10),0) -> 761 | R10: =P10*H10 -> 356855.73 | T10: =I10*G10 -> 1421468.3 | U10: =I10*H10 -> 1352863.1 | V10: =U10-T10 -> -68605.3 | W10: =IFERROR(V10/T10,0) -> -0.048263685
A11: 2025-03-19 | B11: P01783 | C11: CPU | D11: Nova | E11: 16 | F11: 285.57 | G11: 265.46 | H11: 285.57 | I11: 1139 | J11: 17 | K11: =(I11/30)*J11 -> 645.43333 | L11: =IF(E11<K11,"High Risk","Sufficuent Stock") -> High Risk | P11: =ROUNDUP(MAX(0,K11-E11),0) -> 630 | R11: =P11*H11 -> 179909.1 | T11: =I11*G11 -> 302358.94 | U11: =I11*H11 -> 325264.23 | V11: =U11-T11 -> 22905.29 | W11: =IFERROR(V11/T11,0) -> 0.075755293
A12: 2025-10-31 | B12: P00587 | C12: Cooling | D12: Beta | E12: 17 | F12: 485.99 | G12: 452.49 | H12: 485.99 | I12: 1784 | J12: 62 | K12: =(I12/30)*J12 -> 3686.9333 | L12: =IF(E12<K12,"High Risk","Sufficuent Stock") -> High Risk | P12: =ROUNDUP(MAX(0,K12-E12),0) -> 3670 | R12: =P12*H12 -> 1783583.3 | T12: =I12*G12 -> 807242.16 | U12: =I12*H12 -> 867006.16 | V12: =U12-T12 -> 59764 | W12: =IFERROR(V12/T12,0) -> 0.074034785
A13: 2025-11-19 | B13: P01952 | C13: Cooling | D13: Beta | E13: 17 | F13: 12.29 | G13: 12.49 | H13: 12.29 | I13: 1571 | J13: 6 | K13: =(I13/30)*J13 -> 314.2 | L13: =IF(E13<K13,"High Risk","Sufficuent Stock") -> High Risk | P13: =ROUNDUP(MAX(0,K13-E13),0) -> 298 | R13: =P13*H13 -> 3662.42 | T13: =I13*G13 -> 19621.79 | U13: =I13*H13 -> 19307.59 | V13: =U13-T13 -> -314.2 | W13: =IFERROR(V13/T13,0) -> -0.01601281
A14: 2025-09-06 | B14: P02463 | C14: GPU | D14: Alpha | E14: 19 | F14: 234.29 | G14: 218.69 | H14: 234.29 | I14: 2498 | J14: 38 | K14: =(I14/30)*J14 -> 3164.1333 | L14: =IF(E14<K14,"High Risk","Sufficuent Stock") -> High Risk | P14: =ROUNDUP(MAX(0,K14-E14),0) -> 3146 | R14: =P14*H14 -> 737076.34 | T14: =I14*G14 -> 546287.62 | U14: =I14*H14 -> 585256.42 | V14: =U14-T14 -> 38968.8 | W14: =IFERROR(V14/T14,0) -> 0.071333852
... A868: 2025-02-10 | B868: P00504 | C868: Cooling | D868: Beta | E868: 1397 | F868: 199.23 | G868: 206.97 | H868: 199.23 | I868: 3275 | J868: 75 | K868: =(I868/30)*J868 -> 8187.5 | L868: =IF(E868<K868,"High Risk","Sufficuent Stock") -> High Risk | P868: =ROUNDUP(MAX(0,K868-E868),0) -> 6791 | R868: =P868*H868 -> 1352970.9 | T868: =I868*G868 -> 677826.75 | U868: =I868*H868 -> 652478.25 | V868: =U868-T868 -> -25348.5 | W868: =IFERROR(V868/T868,0) -> -0.037396724
A869: 2025-03-09 | B869: P02679 | C869: Board | D869: Sigma | E869: 1397 | F869: 421.87 | G869: 425.13 | H869: 421.87 | I869: 3057 | J869: 82 | K869: =(I869/30)*J869 -> 8355.8 | L869: =IF(E869<K869,"High Risk","Sufficuent Stock") -> High Risk | N869: =COUNTIF(L869:L3868,"High Risk") -> 879 | O869: =N869/COUNTA(B869:B3868) -> 0.41209564 | P869: =ROUNDUP(MAX(0,K869-E869),0) -> 6959 | Q869: =SUM(P869:P3868) -> 2435680 | R869: =P869*H869 -> 2935793.3 | S869: =SUM(R869:R3868) -> 6.2080739e+08 | T869: =I869*G869 -> 1299622.4 | U869: =I869*H869 -> 1289656.6 | V869: =U869-T869 -> -9965.82 | W869: =IFERROR(V869/T869,0) -> -0.0076682427
A870: 2025-03-01 | B870: P00865 | C870: Cooling | D870: Delta | E870: 1399 | F870: 488.8 | G870: 448.99 | H870: 488.8 | I870: 3685 | J870: 85 | K870: =(I870/30)*J870 -> 10440.833 | L870: =IF(E870<K870,"High Risk","Sufficuent Stock") -> High Risk | P870: =ROUNDUP(MAX(0,K870-E870),0) -> 9042 | R870: =P870*H870 -> 4419729.6 | T870: =I870*G870 -> 1654528.2 | U870: =I870*H870 -> 1801228 | V870: =U870-T870 -> 146699.85 | W870: =IFERROR(V870/T870,0) -> 0.088665672
A871: 2025-02-28 | B871: P02942 | C871: CPU | D871: Alpha | E871: 1401 | F871: 115.61 | G871: 117.62 | H871: 115.61 | I871: 3761 | J871: 53 | K871: =(I871/30)*J871 -> 6644.4333 | L871: =IF(E871<K871,"High Risk","Sufficuent Stock") -> High Risk | P871: =ROUNDUP(MAX(0,K871-E871),0) -> 5244 | R871: =P871*H871 -> 606258.84 | T871: =I871*G871 -> 442368.82 | U871: =I871*H871 -> 434809.21 | V871: =U871-T871 -> -7559.61 | W871: =IFERROR(V871/T871,0) -> -0.01708893
A872: 2025-10-16 | B872: P00273 | C872: GPU | D872: Sigma | E872: 1409 | F872: 219.31 | G872: 195.97 | H872: 219.31 | I872: 1852 | J872: 88 | K872: =(I872/30)*J872 -> 5432.5333 | L872: =IF(E872<K872,"High Risk","Sufficuent Stock") -> High Risk | P872: =ROUNDUP(MAX(0,K872-E872),0) -> 4024 | R872: =P872*H872 -> 882503.44 | T872: =I872*G872 -> 362936.44 | U872: =I872*H872 -> 406162.12 | V872: =U872-T872 -> 43225.68 | W872: =IFERROR(V872/T872,0) -> 0.11909986
A873: 2025-03-13 | B873: P01577 | C873: CPU | D873: Sigma | E873: 1410 | F873: 371.02 | G873: 392.86 | H873: 371.02 | I873: 3995 | J873: 35 | K873: =(I873/30)*J873 -> 4660.8333 | L873: =IF(E873<K873,"High Risk","Sufficuent Stock") -> High Risk | P873: =ROUNDUP(MAX(0,K873-E873),0) -> 3251 | R873: =P873*H873 -> 1206186 | T873: =I873*G873 -> 1569475.7 | U873: =I873*H873 -> 1482224.9 | V873: =U873-T873 -> -87250.8 | W873: =IFERROR(V873/T873,0) -> -0.055592323
A874: 2025-06-12 | B874: P01344 | C874: Memory | D874: Beta | E874: 1410 | F874: 295.46 | G874: 304.27 | H874: 295.46 | I874: 3683 | J874: 55 | K874: =(I874/30)*J874 -> 6752.1667 | L874: =IF(E874<K874,"High Risk","Sufficuent Stock") -> High Risk | P874: =ROUNDUP(MAX(0,K874-E874),0) -> 5343 | R874: =P874*H874 -> 1578642.8 | T874: =I874*G874 -> 1120626.4 | U874: =I874*H874 -> 1088179.2 | V874: =U874-T874 -> -32447.23 | W874: =IFERROR(V874/T874,0) -> -0.028954547
A875: 2025-08-18 | B875: P01259 | C875: Board | D875: Nova | E875: 1411 | F875: 255.04 | G875: 277.91 | H875: 255.04 | I875: 833 | J875: 38 | K875: =(I875/30)*J875 -> 1055.1333 | L875: =IF(E875<K875,"High Risk","Sufficuent Stock") -> Sufficuent Stock | P875: =ROUNDUP(MAX(0,K875-E875),0) -> 0 | R875: =P875*H875 -> 0 | T875: =I875*G875 -> 231499.03 | U875: =I875*H875 -> 212448.32 | V875: =U875-T875 -> -19050.71 | W875: =IFERROR(V875/T875,0) -> -0.082292829
A876: 2025-01-30 | B876: P01129 | C876: CPU | D876: Delta | E876: 1412 | F876: 21.9 | G876: 19.56 | H876: 21.9 | I876: 3431 | J876: 70 | K876: =(I876/30)*J876 -> 8005.6667 | L876: =IF(E876<K876,"High Risk","Sufficuent Stock") -> High Risk | P876: =ROUNDUP(MAX(0,K876-E876),0) -> 6594 | R876: =P876*H876 -> 144408.6 | T876: =I876*G876 -> 67110.36 | U876: =I876*H876 -> 75138.9 | V876: =U876-T876 -> 8028.54 | W876: =IFERROR(V876/T876,0) -> 0.1196319
A877: 2025-03-19 | B877: P01081 | C877: GPU | D877: Sigma | E877: 1412 | F877: 427.82 | G877: 441.75 | H877: 427.82 | I877: 1808 | J877: 13 | K877: =(I877/30)*J877 -> 783.46667 | L877: =IF(E877<K877,"High Risk","Sufficuent Stock") -> Sufficuent Stock | P877: =ROUNDUP(MAX(0,K877-E877),0) -> 0 | R877: =P877*H877 -> 0 | T877: =I877*G877 -> 798684 | U877: =I877*H877 -> 773498.56 | V877: =U877-T877 -> -25185.44 | W877: =IFERROR(V877/T877,0) -> -0.031533673
A878: 2025-06-08 | B878: P01643 | C878: GPU | D878: Sigma | E878: 1416 | F878: 27.88 | G878: 28.91 | H878: 27.88 | I878: 1296 | J878: 87 | K878: =(I878/30)*J878 -> 3758.4 | L878: =IF(E878<K878,"High Risk","Sufficuent Stock") -> High Risk | P878: =ROUNDUP(MAX(0,K878-E878),0) -> 2343 | R878: =P878*H878 -> 65322.84 | T878: =I878*G878 -> 37467.36 | U878: =I878*H878 -> 36132.48 | V878: =U878-T878 -> -1334.88 | W878: =IFERROR(V878/T878,0) -> -0.03562781
A879: 2025-04-01 | B879: P01590 | C879: CPU | D879: Sigma | E879: 1417 | F879: 171.39 | G879: 185.27 | H879: 171.39 | I879: 227 | J879: 40 | K879: =(I879/30)*J879 -> 302.66667 | L879: =IF(E879<K879,"High Risk","Sufficuent Stock") -> Sufficuent Stock | P879: =ROUNDUP(MAX(0,K879-E879),0) -> 0 | R879: =P879*H879 -> 0 | T879: =I879*G879 -> 42056.29 | U879: =I879*H879 -> 38905.53 | V879: =U879-T879 -> -3150.76 | W879: =IFERROR(V879/T879,0) -> -0.074917688
A880: 2025-01-14 | B880: P01892 | C880: Memory | D880: Beta | E880: 1420 | F880: 132.33 | G880: 114.39 | H880: 132.33 | I880: 3204 | J880: 23 | K880: =(I880/30)*J880 -> 2456.4 | L880: =IF(E880<K880,"High Risk","Sufficuent Stock") -> High Risk | P880: =ROUNDUP(MAX(0,K880-E880),0) -> 1037 | R880: =P880*H880 -> 137226.21 | T880: =I880*G880 -> 366505.56 | U880: =I880*H880 -> 423985.32 | V880: =U880-T880 -> 57479.76 | W880: =IFERROR(V880/T880,0) -> 0.15683189
A881: 2025-02-23 | B881: P01831 | C881: CPU | D881: Beta | E881: 1423 | F881: 123.99 | G881: 113.68 | H881: 123.99 | I881: 1815 | J881: 81 | K881: =(I881/30)*J881 -> 4900.5 | L881: =IF(E881<K881,"High Risk","Sufficuent Stock") -> High Risk | P881: =ROUNDUP(MAX(0,K881-E881),0) -> 3478 | R881: =P881*H881 -> 431237.22 | T881: =I881*G881 -> 206329.2 | U881: =I881*H881 -> 225041.85 | V881: =U881-T881 -> 18712.65 | W881: =IFERROR(V881/T881,0) -> 0.090693174
... A3001: 2025-01-25 | B3001: P01331 | C3001: CPU | D3001: Nova | E3001: 4998 | F3001: 369.76 | G3001: 324.13 | H3001: 369.76 | I3001: 3368 | J3001: 58 | K3001: =(I3001/30)*J3001 -> 6511.4667 | L3001: =IF(E3001<K3001,"High Risk","Sufficuent Stock") -> High Risk | P3001: =ROUNDUP(MAX(0,K3001-E3001),0) -> 1514 | R3001: =P3001*H3001 -> 559816.64 | T3001: =I3001*G3001 -> 1091669.8 | U3001: =I3001*H3001 -> 1245351.7 | V3001: =U3001-T3001 -> 153681.84 | W3001: =IFERROR(V3001/T3001,0) -> 0.14077685

Sheet Data Quality Checks
A1: Check | B1: Objective | C1: Method | D1: Result | E1: Business Conclusion
A2: Missing Values | B2: לבדוק אo קיימים תאים ריקים בנתונים | C2: COUNTA/countablank | D2: כל העמודות = 3000 | E2: לא נמצאו ערכים חסרים
A3: Duplicates | B3: לבדוק אם קיימים מוצרים כפולים | C3: countif על עמודת PRODUCT ID | D3: =COUNTIF(Inventory!B2:B3001,Inventory!B2) -> 1 | E3: לא נמצאו כפיליות כל ה 3000 בעלי מזהה ייחודי ולכן אין ניפוח של נתוני המלאי ןהביקוש עקב כפיליות
A4: Outliers
A5: Negative Values | B5: לבדוק את עמודת Qty_on_hand | C5: countif על עמודת QTY_ON_HAND | D5: =COUNTIF(Inventory!E2:E3001,"<0") -> 0 | E5: לא נמצאו ערכים שלילליים
A6: Negative Values | B6: לבדוק את עמודת Unit_Cost | C6: countif | D6: =COUNTIF(Inventory!F2:F3001,"<0") -> 0 | E6: לא נמצאו ערכים שלילליים
A7: Negative Values | B7: לבדוק את עמודת std_Cost | C7: countif | D7: =COUNTIF(Inventory!F2:F3001,"<0") -> 0 | E7: לא נמצאו ערכים שלילליים
A8: Negative Values | B8: לבדוק את עמודת Actual_cost | C8: countif | D8: =COUNTIF(Inventory!H2:H3001,"<0") -> 0 | E8: לא נמצאו ערכים שלילליים
A9: Negative Values | B9: לבדוק את עמודת Monthly Demand | C9: countif | D9: =COUNTIF(Inventory!I2:I3001,"<0") -> 0 | E9: לא נמצאו ערכים שלילליים
A10: Negative Values | B10: לבדוק את עמודת Lead_Time_Days | C10: countif | D10: =COUNTIF(Inventory!J2:J3001,"<0") -> 0 | E10: לא נמצאו ערכים שלילליים
A11: Zero_value | B11: לבדוק ערכים 0 בעמודת Qty_on hand | C11: countif | D11: =COUNTIF(Inventory!E2:E3001,0) -> 1 | E11: למוצר אין מלאי, למרות ביקוש חודשי של 3,473 יחידות וזמן אספקה של 65 ימים. יש לבדוק מיד הזמנה פתוחה, מלאי בדרך והצורך בהזמנה דחופה
A12: Zero_value | B12: לבדוק ערכים 0 בעמודת Uמןא
A13: Zero_value
A14: Zero_value
A16: Business Comments
A17: Invalid Dates | B17: לבדוק שכל הערכים בעמודת Date נים | C17: Filter /isnumber | D17: נמצאה רשומה אחת עם תאריך לא תקין | E17: הרשומה נשמרה בשל חשיבבותה אך לא תיכלל בניתוח לפי תקופות עד קבלת התאריך הנכון ממקור הנתונים

Sheet Analysis
A1: Missing Values | H1: Findings & Business Conclusions
H2: ====================================================
A3: Column | B3: Formula | C3: Result | D3: Status
A4: Date | B4: COUNTA(Inventory!#REF!) | C4: =COUNTA(Inventory!A2:A3001) -> 3000 | D4: Passed | H4: DATA QUALITY CHECKS:
A5: Product_ID | B5: COUNTA(Inventory!() | C5: =COUNTA(Inventory!B2:B3001) -> 3000 | D5: Passed
A6: Category | B6: COUNTA(Inventory!() | C6: =COUNTA(Inventory!C2:C3001) -> 3000 | D6: Passed | H6: Missing Values
A7: Supplier | B7: COUNTA(Inventory!() | C7: =COUNTA(Inventory!D2:D3001) -> 3000 | D7: Passed | H7: Duplicates
A8: Qty_On_Hand | B8: COUNTA(Inventory!() | C8: =COUNTA(Inventory!E2:E3001) -> 3000 | D8: Passed | H8: Negative Values
A9: Unit_Cost | B9: COUNTA(Inventory!() | C9: =COUNTA(Inventory!F2:F3001) -> 3000 | D9: Passed | H9: Zero Values
A10: Std_Cost | B10: COUNTA(Inventory!() | C10: =COUNTA(Inventory!G2:G3001) -> 3000 | D10: Passed
A11: Actual_Cost | B11: COUNTA(Inventory!() | C11: =COUNTA(Inventory!H2:H3001) -> 3000 | D11: Passed | H11: ====================================================
A12: Monthly_Demand | B12: COUNTA(Inventory!() | C12: =COUNTA(Inventory!I2:I3001) -> 3000 | D12: Passed
A13: Lead_Time_Days | B13: COUNTA(Inventory!() | C13: =COUNTA(Inventory!J2:J3001) -> 3000 | D13: Passed | H13: BUSINESS FINDINGS:
A15: Duplicates | H15: Finding 1 | I15: Zero Inventory
A17: Column | B17: Formula | C17: Result | D17: Status | I17: Observation
A18: Product_ID | B18: COUNTIF(Inventory!B2:B3001,Inventory!B2) | C18: =COUNTIF(Inventory!B2:B3001,Inventory!B2) -> 1 | D18: Passed | I18: Product P02724, supplied by Beta, has no available stock despite monthly demand of 3,473 units.
A20: Negative Values | I20: Business Impact
A21: Column | B21: Formula | C21: Result | D21: Status | I21: The product has monthly demand of 3,473 units. Therefore, there is a risk of a stockout and lost sales if no open purchase order exists
A22: Qty_On_Hand | B22: COUNTIF(Inventory!D2:D3001,"<0") | C22: =COUNTIF(Inventory!E2:E3001,"<0") -> 0 | D22: Passed
A23: Unit_Cost | B23: cOUNTIF(Inventory!E2:E3001,"<0") | C23: =COUNTIF(Inventory!F2:F3001,"<0") -> 0 | D23: Passed | I23: Recommendation
A24: Std_Cost | B24: COUNTIF(Inventory!F2:F3001,"<0") | C24: =COUNTIF(Inventory!G2:G3001,"<0") -> 0 | D24: Passed | I24: Check whether an open purchase order exists with the supplier. Verify that the inventory data is up to date and, if necessary, place an urgent order.
A25: Actual_Cost | B25: COUNTIF(Inventory!G2:G3001,"<0") | C25: =COUNTIF(Inventory!H2:H3001,"<0") -> 0 | D25: Passed
A26: Monthly_Demand | B26: COUNTIF(Inventory!H2:H3001,"<0") | C26: =COUNTIF(Inventory!I2:I3001,"<0") -> 0 | D26: Passed
A27: Lead_Time_Days | B27: COUNTIF(Inventory!I2:I3001,"<0") | C27: =COUNTIF(Inventory!J2:J3001,"<0") -> 0 | D27: Passed | I27: Inventory Shortage Risk
I28: Observation:
I29: 1,604 out of 3,000 products are classified as High Risk, representing 53.47% of all products.
A30: Zero Values | H30: Finding 2 | I30: Financial Exposure
A31: Column | B31: Formula | C31: Result | D31: Status | I31: Observation:
A32: Qty_On_Hand | B32: COUNTIF(Inventory!E2:E3001,0) | C32: =COUNTIF(Inventory!E2:E3001,0) -> 1 | D32: Review Required | H32: Finding 3 | I32: The total shortage is 4,759,477.5 units, with an estimated value of 1,222,974,681.36.
A33: Unit_Cost | B33: COUNTIF(Inventory!E2:E3001,0) | C33: =COUNTIF(Inventory!F2:F3001,0) -> 0 | D33: Passed | I33: Business Impact:
A34: Std_Cost | B34: COUNTIF(Inventory!F2:F3001,0) | C34: =COUNTIF(Inventory!G2:G3001,0) -> 0 | D34: Passed | I34: The shortage may lead to lost sales, delayed orders and customer dissatisfaction.
A35: Actual_Cost | B35: COUNTIF(Inventory!G2:G3001,0) | C35: =COUNTIF(Inventory!H2:H3001,0) -> 0 | D35: Passed | H35: Finding 4 | I35: Recommendation:
A36: Monthly_Demand | B36: COUNTIF(Inventory!H2:H3001,0) | C36: =COUNTIF(Inventory!I2:I3001,0) -> 0 | D36: Passed | I36: Prioritize Cooling and Memory, which together represent approximately 43.7% of the total shortage value.
A37: Lead_Time_Days | B37: COUNTIF(Inventory!I2:I3001,0) | C37: =COUNTIF(Inventory!J2:J3001,0) -> 0 | D37: Passed | I37: Supplier Exposure
I38: Observation:
I39: Delta has the highest shortage value at 271,714,656.30, representing 22.22% of the total shortage value.
I40: Business Impact:
I41: The exposure is relatively distributed across all five suppliers, indicating that the shortage risk is not caused by a single supplier.
I42: Recommendation:
I43: Prioritize a detailed review with Delta while developing shortage-reduction plans across all suppliers.
H44: Finding 5 | I44: Estimated Inventory Turnover Performance
I45: Observation:
I46: Based on annualized monthly demand, Estimated Annual COGS is 19,200,481,643.16 and Current Inventory Value is 1,956,523,143.90. This results in an Estimated Inventory Turnover of 9.81 and an Estimated Days Inventory Outstanding of 37.19 days
I47: Business Impact:
I48: Based on the current inventory snapshot, the company holds inventory equal to approximately 37 days of estimated COGS. However, the result may still hide excess inventory in some products and shortages in others.
I49: Recommendation:
I50: Monitor turnover by product category and compare beginning and ending inventory balances over time. Once historical inventory balances are available, replace the current inventory value with average inventory to calculate the official Inventory Turnover and DIO.
H51: Finding 6 | I51: Monthly COGS Variance
I52: Observation:
I53: Based on monthly demand, Budget COGS calculated using Standard Cost is 1,518,331,975.26, while Actual COGS calculated using Actual Cost is 1,600,040,136.93. This represents an unfavorable cost variance of 81,708,161.67, or 5.38%.
I54: Business Impact:
I55: Actual product costs are consistently higher than standard costs, increasing the expected cost of meeting monthly demand and potentially reducing gross profit margins.
I56: Recommendation:
I57: Investigate the causes of the higher-than-budget COGS, particularly in Months 3, 5 and 6, and use monthly variance monitoring to identify cost increases early and improve budget control.
H59: Finding 7 | I59: COGS Variance by Category
I60: Observation:
I61: Actual COGS is higher than Budget COGS across all five product categories. GPU recorded the largest unfavorable variance of approximately 18.91 million, followed by Cooling with approximately 18.62 million. Cooling recorded the highest variance rate at approximately 6.12%.
I62: Business Impact:
I63: Cost increases are spread across all categories rather than being limited to one product group. GPU and Cooling together account for approximately 45.9% of the total unfavorable COGS variance, creating a significant risk to gross profit margins.
I64: Recommendation:
I65: Prioritize a detailed review of GPU and Cooling purchasing costs, supplier terms and product mix. Compare Actual Cost with Standard Cost at product level to identify the SKUs and suppliers responsible for the largest variances.
H106: ====================================================

Sheet Dashbord
A1: Inventory Cost and Financial Performance Dashbord
A4: High Risk Products | C4: High Risk Rate | E4: Estimated Inventory Turnover | G4: Estimated Days Inventory Outstanding
A5: =COUNTIF(Inventory!L2:L3001,"High Risk") -> 1604 | C5: =A5/COUNTA(Inventory!B2:B3001) -> 0.53466667 | E5: ='Inventory_kpi''s'!D2 -> 9.8135725 | G5: ='Inventory_kpi''s'!E2 -> 37.193387
A7: Total Shortage Quantity | C7: Total Shortage Value | E7: Estimated Annual COGS | G7: Unfavorable Monthly COGS Variance
A8: =SUM(Inventory!Q2) -> 4760154 | C8: =Inventory!S2 -> 1.2231484e+09 | E8: ='Inventory_kpi''s'!B2 -> 1.9200482e+10 | G8: ='Inventory_kpi''s'!H2 -> 81708162
A39: Portfolio project based on simulated data. Financial values are presented in currency units.

Sheet Data_Dictionaryc
A1: Column | B1: Hebrew | C1: Business Meaning | D1: חשיבות
A2: Date | B2: תאריך | C2: תאריך רכשיה | D2: תאריך העסקה או תאריך רכישת המלאי
A3: Product_ID | B3: קוד מוצר | C3: מזהה ייחודי של המוצר | D3: מזהה ייחודי המשמש למעקב ולניתוח של כל מוצר
A4: Category | B4: קטגוריה | C4: סוג המוצר | D4: מאפשר לנתח ביצועים, רווחיות ורמות מלאי לפי קטגוריות מוצרים.
A5: Supplier | B5: ספקים | C5: ספק שנרכש ממנו המוצר | D5: מאפשר להשוות בין ספקים לפי מחיר, איכות, זמני אספקה וביצועים.
A6: Qty_On_Hand | B6: כמות במלאי | C6: מספר הייחדיות הקימות במלאי | D6: מסייע בזיהוי עודף מלאי או מחסור במלאי
A7: Unit_Cost | B7: עלות ליחידה | C7: המחיר ליחידה | D7: משמש לחישוב ערך המלאי, עלות המכר (COGS) ורווחיות.
A8: Std_Cost | B8: עלות תקנית | C8: העלות שתוכננה בתקציב | D8: עלות מתוכננת המשמשת לתקצוב ולהשוואה מול העלות בפועל
A9: Actual_Cost | B9: עלות בפועל | C9: העלות ששולמה בפועל | D9: משמש לניתוח חריגות בעלות (Variance Analysis) ולהבנת הסיבות להבדלים.
A10: Monthly_Demand | B10: ביקוש חודשי | C10: מספר היחידות שנמכרות בחודש | D10: מסייע בתכנון רכש, תחזיות ומניעת חוסר או עודף מלאי
A11: Lead_Time_Days | B11: זמן אספקה | C11: מספר ימים מההזמה ועד שהמוצר מגיע | D11: מסייע לקבוע מתי לבצע הזמנות כדי למנוע מחסור במלאי.

Sheet Inventory_kpi's
A1: Inventory Performance KPIs | B1: Estimated Annual COGS | C1: Current Inventory Value | D1: Estimated Inventory Turnover | E1: Estimated DIO | F1: Monthly Budget COGS | G1: Monthly Actual COGS | H1: COGS Variance | I1: COGS Variance%
B2: =G2*12 -> 1.9200482e+10 | C2: =SUMPRODUCT(Inventory!E2:E3001,Inventory!H2:H3001) -> 1.9565231e+09 | D2: =B2/C2 -> 9.8135725 | E2: =365/D2 -> 37.193387 | F2: =SUM(Inventory!T2:T3001) -> 1.518332e+09 | G2: =SUM(Inventory!U2:U3001) -> 1.6000401e+09 | H2: =G2-F2 -> 81708162 | I2: =IFERROR(H2/F2,0) -> 0.053814425

Sheet Budget_vs_Actual
A1: Month | B1: Budget_COGS | C1: Actual_COGS | D1: Budget_Inventory | E1: Actual_Inventory | F1: COGS Variance | G1: COGS Variance % | H1: COGS Status | I1: Favorable Months | J1: Unfavorable month | K1: Inventory Variance | L1: Inventory Variance % | M1: Inventory Status | N1: Above Budget Months | O1: Below Budget Months
A2: 1 | B2: 653502 | C2: 634511 | D2: 1243759 | E2: 1458735 | F2: =C2-B2 -> -18991 | G2: =IFERROR(F2/B2,0) -> -0.029060355 | H2: =IF(G2<=0,"Favorable","Unfavorable") -> Favorable | I2: =COUNTIF(H2:H13,"Favorable") -> 6 | J2: =COUNTIF(H2:H13,"Unfavorable") -> 6 | K2: =E2-D2 -> 214976 | L2: =IFERROR(K2/D2,0) -> 0.17284377 | M2: =IF(K2>0,"Above Budget",IF(K2<0,"Below Budget","On Budget")) -> Above Budget | N2: =COUNTIF(M2:M13,"Above Budget") -> 9 | O2: =COUNTIF(M2:M13,"Below Budget") -> 3
A3: 2 | B3: 454079 | C3: 415822 | D3: 1154689 | E3: 1344629 | F3: =C3-B3 -> -38257 | G3: =IFERROR(F3/B3,0) -> -0.084251859 | H3: =IF(G3<=0,"Favorable","Unfavorable") -> Favorable | K3: =E3-D3 -> 189940 | L3: =IFERROR(K3/D3,0) -> 0.16449451 | M3: =IF(K3>0,"Above Budget",IF(K3<0,"Below Budget","On Budget")) -> Above Budget
A4: 3 | B4: 506173 | C4: 572039 | D4: 1229753 | E4: 1225052 | F4: =C4-B4 -> 65866 | G4: =IFERROR(F4/B4,0) -> 0.13012547 | H4: =IF(G4<=0,"Favorable","Unfavorable") -> Unfavorable | K4: =E4-D4 -> -4701 | L4: =IFERROR(K4/D4,0) -> -0.0038227189 | M4: =IF(K4>0,"Above Budget",IF(K4<0,"Below Budget","On Budget")) -> Below Budget
A5: 4 | B5: 533611 | C5: 499549 | D5: 1113956 | E5: 1297111 | F5: =C5-B5 -> -34062 | G5: =IFERROR(F5/B5,0) -> -0.063833017 | H5: =IF(G5<=0,"Favorable","Unfavorable") -> Favorable | K5: =E5-D5 -> 183155 | L5: =IFERROR(K5/D5,0) -> 0.16441852 | M5: =IF(K5>0,"Above Budget",IF(K5<0,"Below Budget","On Budget")) -> Above Budget
A6: 5 | B6: 484313 | C6: 538648 | D6: 1253816 | E6: 1458986 | F6: =C6-B6 -> 54335 | G6: =IFERROR(F6/B6,0) -> 0.11218984 | H6: =IF(G6<=0,"Favorable","Unfavorable") -> Unfavorable | K6: =E6-D6 -> 205170 | L6: =IFERROR(K6/D6,0) -> 0.16363645 | M6: =IF(K6>0,"Above Budget",IF(K6<0,"Below Budget","On Budget")) -> Above Budget
A7: 6 | B7: 515444 | C7: 576276 | D7: 1163970 | E7: 1284174 | F7: =C7-B7 -> 60832 | G7: =IFERROR(F7/B7,0) -> 0.11801864 | H7: =IF(G7<=0,"Favorable","Unfavorable") -> Unfavorable | K7: =E7-D7 -> 120204 | L7: =IFERROR(K7/D7,0) -> 0.1032707 | M7: =IF(K7>0,"Above Budget",IF(K7<0,"Below Budget","On Budget")) -> Above Budget
A8: 7 | B8: 450256 | C8: 437086 | D8: 1166065 | E8: 1206802 | F8: =C8-B8 -> -13170 | G8: =IFERROR(F8/B8,0) -> -0.029250027 | H8: =IF(G8<=0,"Favorable","Unfavorable") -> Favorable | K8: =E8-D8 -> 40737 | L8: =IFERROR(K8/D8,0) -> 0.034935445 | M8: =IF(K8>0,"Above Budget",IF(K8<0,"Below Budget","On Budget")) -> Above Budget
A9: 8 | B9: 403676 | C9: 433247 | D9: 1078882 | E9: 980357 | F9: =C9-B9 -> 29571 | G9: =IFERROR(F9/B9,0) -> 0.073254293 | H9: =IF(G9<=0,"Favorable","Unfavorable") -> Unfavorable | K9: =E9-D9 -> -98525 | L9: =IFERROR(K9/D9,0) -> -0.091321386 | M9: =IF(K9>0,"Above Budget",IF(K9<0,"Below Budget","On Budget")) -> Below Budget
A10: 9 | B10: 693525 | C10: 721824 | D10: 1172394 | E10: 1100403 | F10: =C10-B10 -> 28299 | G10: =IFERROR(F10/B10,0) -> 0.040804585 | H10: =IF(G10<=0,"Favorable","Unfavorable") -> Unfavorable | K10: =E10-D10 -> -71991 | L10: =IFERROR(K10/D10,0) -> -0.061405125 | M10: =IF(K10>0,"Above Budget",IF(K10<0,"Below Budget","On Budget")) -> Below Budget
A11: 10 | B11: 521742 | C11: 535065 | D11: 1273220 | E11: 1288926 | F11: =C11-B11 -> 13323 | G11: =IFERROR(F11/B11,0) -> 0.02553561 | H11: =IF(G11<=0,"Favorable","Unfavorable") -> Unfavorable | K11: =E11-D11 -> 15706 | L11: =IFERROR(K11/D11,0) -> 0.012335653 | M11: =IF(K11>0,"Above Budget",IF(K11<0,"Below Budget","On Budget")) -> Above Budget
A12: 11 | B12: 526769 | C12: 518532 | D12: 1072610 | E12: 1206382 | F12: =C12-B12 -> -8237 | G12: =IFERROR(F12/B12,0) -> -0.015636835 | H12: =IF(G12<=0,"Favorable","Unfavorable") -> Favorable | K12: =E12-D12 -> 133772 | L12: =IFERROR(K12/D12,0) -> 0.12471635 | M12: =IF(K12>0,"Above Budget",IF(K12<0,"Below Budget","On Budget")) -> Above Budget
A13: 12 | B13: 618870 | C13: 565680 | D13: 1174568 | E13: 1185717 | F13: =C13-B13 -> -53190 | G13: =IFERROR(F13/B13,0) -> -0.085946968 | H13: =IF(G13<=0,"Favorable","Unfavorable") -> Favorable | K13: =E13-D13 -> 11149 | L13: =IFERROR(K13/D13,0) -> 0.0094920005 | M13: =IF(K13>0,"Above Budget",IF(K13<0,"Below Budget","On Budget")) -> Above Budget

Sheet Project_Roadmap
A1: Week | B1: Task | C1: Deliverable
A2: 1 | B2: Understand the data and build data dictionary | C2: Data Dictionary
A3: 1 | B3: Clean the data and identify anomalies | C3: Clean dataset
A4: 2 | B4: Calculate KPIs | C4: KPI table
A5: 2 | B5: Variance Analysis | C5: PPV & Budget vs Actual
A6: 3 | B6: Inventory Analysis | C6: ABC, Aging, Slow Moving
A7: 3 | B7: Executive Dashboard | C7: Excel dashboard
A8: 4 | B8: Management Presentation | C8: 1-page summary + LinkedIn post

Sheet Business_Questions
A1: ID | B1: Question
A2: 1 | B2: Which supplier has the highest purchase price variance (PPV)?
A3: 2 | B3: Which products are overstocked?
A4: 3 | B4: Which products are slow moving?
A5: 4 | B5: What is the inventory turnover?
A6: 5 | B6: Which category has the highest inventory value?
A7: 6 | B7: Where is Budget vs Actual variance above 10%?
A8: 7 | B8: What recommendations would you give management?
